sponsors/views.py
sponsors/apps.py
sponsors/urls.py
sponsors/models.py
sponsors/admin.py
sponsors/__init__.py
sponsors/app_settings.py
sponsors/templates/sponsors/sponsors_list.html
sponsors/templates/sponsors/sponsors_tag_unit.html
sponsors/templates/sponsors/base.html
sponsors/templates/sponsors/sponsors_tag.html
sponsors/tests/settings.py
sponsors/tests/test_views.py
sponsors/tests/test_models.py
sponsors/tests/urls.py
sponsors/tests/test_templatetags.py
sponsors/tests/__init__.py
sponsors/static/sponsors/css/sponsors.css
sponsors/templatetags/sponsors_extras.py
sponsors/templatetags/__init__.py
django_sponsors-0.1.1.dist-info/metadata.json
django_sponsors-0.1.1.dist-info/METADATA
django_sponsors-0.1.1.dist-info/RECORD
django_sponsors-0.1.1.dist-info/DESCRIPTION.rst
django_sponsors-0.1.1.dist-info/WHEEL
django_sponsors-0.1.1.dist-info/top_level.txt
