Metadata-Version: 2.0
Name: django-sponsors
Version: 0.1.1
Summary: Django App to easily manage project sponsors
Home-page: https://github.com/miguelfg/django-sponsors
Author: Miguel Fiandor
Author-email: miguel.fiandor.gutierrez@gmail.com
License: MIT
Keywords: django,sponsors,sponsor,logos,logo
Platform: UNKNOWN
Classifier: Development Status :: 3 - Alpha
Classifier: Framework :: Django
Classifier: Intended Audience :: Developers
Classifier: License :: OSI Approved :: MIT License
Classifier: Natural Language :: English
Classifier: Programming Language :: Python
Classifier: Programming Language :: Python :: 2
Classifier: Programming Language :: Python :: 2.6
Classifier: Programming Language :: Python :: 2.7
Classifier: Programming Language :: Python :: 3
Classifier: Programming Language :: Python :: 3.2
Classifier: Programming Language :: Python :: 3.3
Classifier: Programming Language :: Python :: 3.4
Classifier: Framework :: Django
Classifier: Framework :: Django :: 1.6
Classifier: Framework :: Django :: 1.7
Classifier: Framework :: Django :: 1.8
Requires-Dist: python-dateutil
Requires-Dist: django-stdimage
